{
    "name": "Banque des Lutins",
    "shortName": "Banque des Lutins",
    "x": 0,
    "y": 0,
    "visibleBoundsMinX": -10,
    "visibleBoundsMaxX": 10,
    "visibleBoundsMinY": -10,
    "visibleBoundsMaxY": 10,
    "z_levels": [
        {
            "z": 0,
            "z-name": "Banque",
            "visibleBoundsMinX": -10,
            "visibleBoundsMaxX": 10,
            "visibleBoundsMinY": -10,
            "visibleBoundsMaxY": 10
        }
    ],
    "biomes": [
        {
            "wall": "arbre3",
            "ressource": "bois"
        },
        {
            "wall": "pierre3",
            "ressource": "pierre"
        }
    ]
}